{
  "title": "Many Glaciers Lodge",
  "indexDescription": "Photos from Glacier National Park & Many Glaciers lodge.",
  "description": "Photos from Glacier National Park near the Many Glaciers lodge. We stayed two nights on a road trip to Montana in June.",
  "cNum": 1,
  "ready": true,
  "indexThumbnail": "/tin/c1-5-t.jpg",
  "width": 480,
  "height": 480,
  "posted": "2023-06-12",
  "images": [
    {
      "iPreview": "/images/c1/c1-5-p.jpg",
      "iThumbnail": "/images/c1/c1-5-t.jpg",
      "title": "Swiftcurrent Lake",
      "description": "We walked around Swiftcurrent Lake and Lake Josephine. They are connected with a slow moving river shown here. You can see Mount Henkel, the red mountain in the background.",
      "width": 4032,
      "height": 3024,
      "size": 4843825,
      "sizet": 87322
    },
    {
      "iPreview": "/images/c1/c1-3-p.jpg",
      "iThumbnail": "/images/c1/c1-3-t.jpg",
      "title": "Many Glaciers Lodge",
      "description": "This is the smaller south wing of the lodge. The north wing is on the right out of the picture. We stayed in the room one from the left end with the deck. We had a great view of the mountains. Every view is spectacular.",
      "width": 4032,
      "height": 3024,
      "size": 4040403,
      "sizet": 81188
    },
    {
      "iPreview": "/images/c1/c1-1-p.jpg",
      "iThumbnail": "/images/c1/c1-1-t.jpg",
      "title": "Many Glaciers Fireplace",
      "description": "I was amazed how well the fireplace hood worked. The one we made for the cabin that smoked like crazy so we cut it up and turned it into a planter.",
      "width": 3024,
      "height": 4032,
      "size": 2797506,
      "sizet": 71810
    },
    {
      "iPreview": "/images/c1/c1-4-p.jpg",
      "iThumbnail": "/images/c1/c1-4-t.jpg",
      "title": "Mount Grinnell",
      "description": "Mount Grinnel is right across the lake from the lodge.  We had great weather.",
      "width": 4032,
      "height": 3024,
      "size": 3834135,
      "sizet": 71680
    },
    {
      "iPreview": "/images/c1/c1-7-p.jpg",
      "iThumbnail": "/images/c1/c1-7-t.jpg",
      "title": "Lake Trail",
      "description": "We hiked around the two lakes near the Many Glaciers Lodge with our bear spray handy.",
      "width": 3024,
      "height": 4032,
      "size": 2458238,
      "sizet": 120478
    },
    {
      "iPreview": "/images/c1/c1-2-p.jpg",
      "iThumbnail": "/images/c1/c1-2-t.jpg",
      "title": "Swiftcurrent Lake",
      "description": "A evening view south from Many Glaciers Lodge over Swiftcurrent Lake.",
      "width": 4032,
      "height": 3024,
      "size": 3871458,
      "sizet": 70466
    },
    {
      "iPreview": "/images/c1/c1-6-p.jpg",
      "iThumbnail": "/images/c1/c1-6-t.jpg",
      "title": "Moose Land",
      "description": "We saw a moose on the far side of the lake and Kathleen filmed it.",
      "width": 4032,
      "height": 3024,
      "size": 3265476,
      "sizet": 62027
    },
    {
      "iPreview": "/images/c1/c1-8-p.jpg",
      "iThumbnail": "/images/c1/c1-8-t.jpg",
      "title": "Two Red Rocks",
      "description": "The two red rocks are having a great time sliding down the hill into the river. They’re living at a time scale hard for us to imagine. We saw two other red rocks swimming in the lake but I didn’t get a picture of that.",
      "width": 2556,
      "height": 2556,
      "size": 1831865,
      "sizet": 92666
    }
  ],
  "zoomPoints": {
    "430x784": [
      {
        "scale": 0.22,
        "tx": -100.12,
        "ty": -29.6
      },
      {
        "scale": 0.27,
        "tx": -255.25,
        "ty": -18.65
      },
      {
        "scale": 0.32,
        "tx": -466.06,
        "ty": -182.31
      },
      {
        "scale": 0.28,
        "tx": -233.4,
        "ty": -55.5
      },
      {
        "scale": 0.34,
        "tx": -464.08,
        "ty": -107.91
      },
      {
        "scale": 0.28,
        "tx": -162.95,
        "ty": -30.97
      },
      {
        "scale": 0.27,
        "tx": -2.14,
        "ty": -47.87
      },
      {
        "scale": 0.38,
        "tx": -200.31,
        "ty": -98.15
      }
    ],
    "430x933": [
      {
        "scale": 0.3869725745122703,
        "tx": -504.3377462894156,
        "ty": -3.136298286709803
      },
      {
        "scale": 0.3133355925978119,
        "tx": -478.3290788088499,
        "ty": -5.981940115612019
      },
      {
        "scale": 0.2341567652845332,
        "tx": -115.7301688666828,
        "ty": -2.425458734821817
      },
      {
        "scale": 0.4328213234068456,
        "tx": -471.9789819047052,
        "ty": -6.204496801996726
      },
      {
        "scale": 0.3323842330710334,
        "tx": -5.240082277291208,
        "ty": -52.76019829740903
      },
      {
        "scale": 0.6125446048460158,
        "tx": -929.421949591763,
        "ty": -223.8618349853446
      },
      {
        "scale": 0.3949076433392298,
        "tx": -157.7491027117248,
        "ty": -15.272493233219
      },
      {
        "scale": 0.49,
        "tx": -322.34,
        "ty": -156.03
      }
    ],
    "932x490": [
      {
        "scale": 0.4,
        "tx": -11.31,
        "ty": -789.62
      },
      {
        "scale": 0.23,
        "tx": 0,
        "ty": 0
      },
      {
        "scale": 0.25,
        "tx": -2.66,
        "ty": -175.86
      },
      {
        "scale": 0.24,
        "tx": -13.81,
        "ty": -57.75
      },
      {
        "scale": 0.24,
        "tx": -10.13,
        "ty": -59.45
      },
      {
        "scale": 0.24,
        "tx": -4.66,
        "ty": -65.65
      },
      {
        "scale": 0.53,
        "tx": -3.95,
        "ty": -71.52
      },
      {
        "scale": 0.43,
        "tx": -84.59,
        "ty": -360.34
      }
    ],
    "932x430": [
      {
        "scale": 0.26054360621930783,
        "tx": -33.270952758272756,
        "ty": -114.55340172091621
      },
      {
        "scale": 0.27834250277608774,
        "tx": -177.96266306212584,
        "ty": -318.8611765966142
      },
      {
        "scale": 0.32072341077583505,
        "tx": -33.14815332280219,
        "ty": -600.4438297778165
      },
      {
        "scale": 0.24236370344360184,
        "tx": -0.4093978486742298,
        "ty": -64.31064269711659
      },
      {
        "scale": 0.4268800093698226,
        "tx": -25.09200690515189,
        "ty": -183.61200873837805
      },
      {
        "scale": 0.2565651407764188,
        "tx": -70.56363281949075,
        "ty": -38.77789720316832
      },
      {
        "scale": 0.23931200095198624,
        "tx": -19.743954155899445,
        "ty": -56.50124464930424
      },
      {
        "scale": 0.374089887783506,
        "tx": -6.4909295033135805,
        "ty": -348.04864755602625
      }
    ]
  }
}